{
  "item": [
    {
      "id": "53f549a8-27dd-4ad8-a22e-3018bb816ea1",
      "name": "Get",
      "description": {
        "content": "",
        "type": "text/plain"
      },
      "item": [
        {
          "id": "a99dccb8-892e-4359-b1da-4dda0e1cf25a",
          "name": "GitHub Get License",
          "request": {
            "name": "GitHub Get License",
            "description": {
              "content": "The GitHub Licenses API endpoint `/licenses/{license}` allows developers to retrieve detailed information about a specific open source license by providing its unique license key as a path parameter. When you make a GET request to this endpoint, it returns comprehensive details about the specified license, including its full name, description, permissions, conditions, limitations, and the complete license text. This is particularly useful when you need to programmatically access license information for compliance purposes, display license details in your application, or help users understand the terms of a particular open source license before applying it to their repository.",
              "type": "text/plain"
            },
            "url": {
              "path": [
                "licenses",
                ":license"
              ],
              "host": [
                "{{baseUrl}}"
              ],
              "query": [],
              "variable": [
                {
                  "disabled": false,
                  "type": "any",
                  "value": "<string>",
                  "key": "license",
                  "description": "(Required) "
                },
                {
                  "description": "Self-hosted Enterprise Server hostname",
                  "type": "any",
                  "value": "{{hostname}}",
                  "key": "hostname"
                },
                {
                  "description": "Self-hosted Enterprise Server protocol",
                  "type": "any",
                  "value": "{{protocol}}",
                  "key": "protocol"
                }
              ]
            },
            "header": [
              {
                "key": "Accept",
                "value": "application/json"
              }
            ],
            "method": "GET",
            "auth": {
              "type": "bearer",
              "bearer": [
                {
                  "key": "token",
                  "value": "{{bearerToken}}"
                }
              ]
            }
          },
          "response": [
            {
              "id": "991ebe24-399b-4195-8d09-0ff72c0af24f",
              "name": "Response",
              "originalRequest": {
                "url": {
                  "path": [
                    "licenses",
                    ":license"
                  ],
                  "host": [
                    "{{baseUrl}}"
                  ],
                  "query": [],
                  "variable": [
                    {
                      "disabled": false,
                      "type": "any",
                      "value": "<string>",
                      "key": "license",
                      "description": "(Required) "
                    },
                    {
                      "description": "Self-hosted Enterprise Server hostname",
                      "type": "any",
                      "value": "{{hostname}}",
                      "key": "hostname"
                    },
                    {
                      "description": "Self-hosted Enterprise Server protocol",
                      "type": "any",
                      "value": "{{protocol}}",
                      "key": "protocol"
                    }
                  ]
                },
                "header": [
                  {
                    "description": {
                      "content": "Added as a part of security scheme: bearer",
                      "type": "text/plain"
                    },
                    "key": "Authorization",
                    "value": "Bearer <token>"
                  },
                  {
                    "key": "Accept",
                    "value": "application/json"
                  }
                ],
                "method": "GET",
                "body": {}
              },
              "status": "OK",
              "code": 200,
              "header": [
                {
                  "key": "Content-Type",
                  "value": "application/json"
                }
              ],
              "body": "{\n  \"key\": \"mit\",\n  \"name\": \"MIT License\",\n  \"spdx_id\": \"MIT\",\n  \"url\": \"https://api.github.com/licenses/mit\",\n  \"node_id\": \"MDc6TGljZW5zZW1pdA==\",\n  \"html_url\": \"http://choosealicense.com/licenses/mit/\",\n  \"description\": \"A permissive license that is short and to the point. It lets people do anything with your code with proper attribution and without warranty.\",\n  \"implementation\": \"Create a text file (typically named LICENSE or LICENSE.txt) in the root of your source code and copy the text of the license into the file. Replace [year] with the current year and [fullname] with the name (or names) of the copyright holders.\",\n  \"permissions\": [\n    \"commercial-use\",\n    \"modifications\",\n    \"distribution\",\n    \"sublicense\",\n    \"private-use\"\n  ],\n  \"conditions\": [\n    \"include-copyright\"\n  ],\n  \"limitations\": [\n    \"no-liability\"\n  ],\n  \"body\": \"\\n\\nThe MIT License (MIT)\\n\\nCopyright (c) [year] [fullname]\\n\\nPermission is hereby granted, free of charge, to any person obtaining a copy\\nof this software and associated documentation files (the \\\"Software\\\"), to deal\\nin the Software without restriction, including without limitation the rights\\nto use, copy, modify, merge, publish, distribute, sublicense, and/or sell\\ncopies of the Software, and to permit persons to whom the Software is\\nfurnished to do so, subject to the following conditions:\\n\\nThe above copyright notice and this permission notice shall be included in all\\ncopies or substantial portions of the Software.\\n\\nTHE SOFTWARE IS PROVIDED \\\"AS IS\\\", WITHOUT WARRANTY OF ANY KIND, EXPRESS OR\\nIMPLIED, INCLUDING BUT NOT LIMITED TO THE WARRANTIES OF MERCHANTABILITY,\\nFITNESS FOR A PARTICULAR PURPOSE AND NONINFRINGEMENT. IN NO EVENT SHALL THE\\nAUTHORS OR COPYRIGHT HOLDERS BE LIABLE FOR ANY CLAIM, DAMAGES OR OTHER\\nLIABILITY, WHETHER IN AN ACTION OF CONTRACT, TORT OR OTHERWISE, ARISING FROM,\\nOUT OF OR IN CONNECTION WITH THE SOFTWARE OR THE USE OR OTHER DEALINGS IN THE\\nSOFTWARE.\\n\",\n  \"featured\": true\n}",
              "cookie": [],
              "_postman_previewlanguage": "json"
            },
            {
              "id": "00fab827-4213-4b57-af01-31739e06bcfe",
              "name": "Not modified",
              "originalRequest": {
                "url": {
                  "path": [
                    "licenses",
                    ":license"
                  ],
                  "host": [
                    "{{baseUrl}}"
                  ],
                  "query": [],
                  "variable": [
                    {
                      "disabled": false,
                      "type": "any",
                      "value": "<string>",
                      "key": "license",
                      "description": "(Required) "
                    },
                    {
                      "description": "Self-hosted Enterprise Server hostname",
                      "type": "any",
                      "value": "{{hostname}}",
                      "key": "hostname"
                    },
                    {
                      "description": "Self-hosted Enterprise Server protocol",
                      "type": "any",
                      "value": "{{protocol}}",
                      "key": "protocol"
                    }
                  ]
                },
                "header": [
                  {
                    "description": {
                      "content": "Added as a part of security scheme: bearer",
                      "type": "text/plain"
                    },
                    "key": "Authorization",
                    "value": "Bearer <token>"
                  }
                ],
                "method": "GET",
                "body": {}
              },
              "status": "Not Modified",
              "code": 304,
              "header": [
                {
                  "key": "Content-Type",
                  "value": "text/plain"
                }
              ],
              "body": "",
              "cookie": [],
              "_postman_previewlanguage": "text"
            },
            {
              "id": "b9c63ee1-a355-4f76-ab45-0d5440fe6a10",
              "name": "Forbidden",
              "originalRequest": {
                "url": {
                  "path": [
                    "licenses",
                    ":license"
                  ],
                  "host": [
                    "{{baseUrl}}"
                  ],
                  "query": [],
                  "variable": [
                    {
                      "disabled": false,
                      "type": "any",
                      "value": "<string>",
                      "key": "license",
                      "description": "(Required) "
                    },
                    {
                      "description": "Self-hosted Enterprise Server hostname",
                      "type": "any",
                      "value": "{{hostname}}",
                      "key": "hostname"
                    },
                    {
                      "description": "Self-hosted Enterprise Server protocol",
                      "type": "any",
                      "value": "{{protocol}}",
                      "key": "protocol"
                    }
                  ]
                },
                "header": [
                  {
                    "description": {
                      "content": "Added as a part of security scheme: bearer",
                      "type": "text/plain"
                    },
                    "key": "Authorization",
                    "value": "Bearer <token>"
                  },
                  {
                    "key": "Accept",
                    "value": "application/json"
                  }
                ],
                "method": "GET",
                "body": {}
              },
              "status": "Forbidden",
              "code": 403,
              "header": [
                {
                  "key": "Content-Type",
                  "value": "application/json"
                }
              ],
              "body": "{\n  \"message\": \"Example body text\",\n  \"documentation_url\": \"https://api.github.com/repos/octocat/Hello-World\",\n  \"url\": \"https://api.github.com/repos/octocat/Hello-World\",\n  \"status\": \"open\"\n}",
              "cookie": [],
              "_postman_previewlanguage": "json"
            },
            {
              "id": "13487c06-c367-4ecb-9b26-f63ee1faa23e",
              "name": "Resource not found",
              "originalRequest": {
                "url": {
                  "path": [
                    "licenses",
                    ":license"
                  ],
                  "host": [
                    "{{baseUrl}}"
                  ],
                  "query": [],
                  "variable": [
                    {
                      "disabled": false,
                      "type": "any",
                      "value": "<string>",
                      "key": "license",
                      "description": "(Required) "
                    },
                    {
                      "description": "Self-hosted Enterprise Server hostname",
                      "type": "any",
                      "value": "{{hostname}}",
                      "key": "hostname"
                    },
                    {
                      "description": "Self-hosted Enterprise Server protocol",
                      "type": "any",
                      "value": "{{protocol}}",
                      "key": "protocol"
                    }
                  ]
                },
                "header": [
                  {
                    "description": {
                      "content": "Added as a part of security scheme: bearer",
                      "type": "text/plain"
                    },
                    "key": "Authorization",
                    "value": "Bearer <token>"
                  },
                  {
                    "key": "Accept",
                    "value": "application/json"
                  }
                ],
                "method": "GET",
                "body": {}
              },
              "status": "Not Found",
              "code": 404,
              "header": [
                {
                  "key": "Content-Type",
                  "value": "application/json"
                }
              ],
              "body": "{\n  \"message\": \"Example body text\",\n  \"documentation_url\": \"https://api.github.com/repos/octocat/Hello-World\",\n  \"url\": \"https://api.github.com/repos/octocat/Hello-World\",\n  \"status\": \"open\"\n}",
              "cookie": [],
              "_postman_previewlanguage": "json"
            }
          ],
          "event": [],
          "protocolProfileBehavior": {
            "disableBodyPruning": true
          }
        }
      ],
      "event": []
    },
    {
      "id": "60a0b800-f430-4156-adfc-7c9a0e4d9e41",
      "name": "Licenses",
      "description": {
        "content": "",
        "type": "text/plain"
      },
      "item": [
        {
          "id": "175191c5-6d1f-435a-9764-5c65e1d98545",
          "name": "GitHub Get License",
          "request": {
            "name": "GitHub Get License",
            "description": {
              "content": "The GitHub Licenses API endpoint `/licenses/{license}` allows developers to retrieve detailed information about a specific open source license by providing its unique license key as a path parameter. When you make a GET request to this endpoint, it returns comprehensive details about the specified license, including its full name, description, permissions, conditions, limitations, and the complete license text. This is particularly useful when you need to programmatically access license information for compliance purposes, display license details in your application, or help users understand the terms of a particular open source license before applying it to their repository.",
              "type": "text/plain"
            },
            "url": {
              "path": [
                "licenses",
                ":license"
              ],
              "host": [
                "{{baseUrl}}"
              ],
              "query": [],
              "variable": [
                {
                  "disabled": false,
                  "type": "any",
                  "value": "<string>",
                  "key": "license",
                  "description": "(Required) "
                },
                {
                  "description": "Self-hosted Enterprise Server hostname",
                  "type": "any",
                  "value": "{{hostname}}",
                  "key": "hostname"
                },
                {
                  "description": "Self-hosted Enterprise Server protocol",
                  "type": "any",
                  "value": "{{protocol}}",
                  "key": "protocol"
                }
              ]
            },
            "header": [
              {
                "key": "Accept",
                "value": "application/json"
              }
            ],
            "method": "GET",
            "auth": {
              "type": "bearer",
              "bearer": [
                {
                  "key": "token",
                  "value": "{{bearerToken}}"
                }
              ]
            }
          },
          "response": [
            {
              "id": "43261fd4-2415-4af3-83e9-0799187ca324",
              "name": "Response",
              "originalRequest": {
                "url": {
                  "path": [
                    "licenses",
                    ":license"
                  ],
                  "host": [
                    "{{baseUrl}}"
                  ],
                  "query": [],
                  "variable": [
                    {
                      "disabled": false,
                      "type": "any",
                      "value": "<string>",
                      "key": "license",
                      "description": "(Required) "
                    },
                    {
                      "description": "Self-hosted Enterprise Server hostname",
                      "type": "any",
                      "value": "{{hostname}}",
                      "key": "hostname"
                    },
                    {
                      "description": "Self-hosted Enterprise Server protocol",
                      "type": "any",
                      "value": "{{protocol}}",
                      "key": "protocol"
                    }
                  ]
                },
                "header": [
                  {
                    "description": {
                      "content": "Added as a part of security scheme: bearer",
                      "type": "text/plain"
                    },
                    "key": "Authorization",
                    "value": "Bearer <token>"
                  },
                  {
                    "key": "Accept",
                    "value": "application/json"
                  }
                ],
                "method": "GET",
                "body": {}
              },
              "status": "OK",
              "code": 200,
              "header": [
                {
                  "key": "Content-Type",
                  "value": "application/json"
                }
              ],
              "body": "{\n  \"key\": \"mit\",\n  \"name\": \"MIT License\",\n  \"spdx_id\": \"MIT\",\n  \"url\": \"https://api.github.com/licenses/mit\",\n  \"node_id\": \"MDc6TGljZW5zZW1pdA==\",\n  \"html_url\": \"http://choosealicense.com/licenses/mit/\",\n  \"description\": \"A permissive license that is short and to the point. It lets people do anything with your code with proper attribution and without warranty.\",\n  \"implementation\": \"Create a text file (typically named LICENSE or LICENSE.txt) in the root of your source code and copy the text of the license into the file. Replace [year] with the current year and [fullname] with the name (or names) of the copyright holders.\",\n  \"permissions\": [\n    \"commercial-use\",\n    \"modifications\",\n    \"distribution\",\n    \"sublicense\",\n    \"private-use\"\n  ],\n  \"conditions\": [\n    \"include-copyright\"\n  ],\n  \"limitations\": [\n    \"no-liability\"\n  ],\n  \"body\": \"\\n\\nThe MIT License (MIT)\\n\\nCopyright (c) [year] [fullname]\\n\\nPermission is hereby granted, free of charge, to any person obtaining a copy\\nof this software and associated documentation files (the \\\"Software\\\"), to deal\\nin the Software without restriction, including without limitation the rights\\nto use, copy, modify, merge, publish, distribute, sublicense, and/or sell\\ncopies of the Software, and to permit persons to whom the Software is\\nfurnished to do so, subject to the following conditions:\\n\\nThe above copyright notice and this permission notice shall be included in all\\ncopies or substantial portions of the Software.\\n\\nTHE SOFTWARE IS PROVIDED \\\"AS IS\\\", WITHOUT WARRANTY OF ANY KIND, EXPRESS OR\\nIMPLIED, INCLUDING BUT NOT LIMITED TO THE WARRANTIES OF MERCHANTABILITY,\\nFITNESS FOR A PARTICULAR PURPOSE AND NONINFRINGEMENT. IN NO EVENT SHALL THE\\nAUTHORS OR COPYRIGHT HOLDERS BE LIABLE FOR ANY CLAIM, DAMAGES OR OTHER\\nLIABILITY, WHETHER IN AN ACTION OF CONTRACT, TORT OR OTHERWISE, ARISING FROM,\\nOUT OF OR IN CONNECTION WITH THE SOFTWARE OR THE USE OR OTHER DEALINGS IN THE\\nSOFTWARE.\\n\",\n  \"featured\": true\n}",
              "cookie": [],
              "_postman_previewlanguage": "json"
            },
            {
              "id": "e35c7c5a-3313-406c-addc-758b0cd9c732",
              "name": "Not modified",
              "originalRequest": {
                "url": {
                  "path": [
                    "licenses",
                    ":license"
                  ],
                  "host": [
                    "{{baseUrl}}"
                  ],
                  "query": [],
                  "variable": [
                    {
                      "disabled": false,
                      "type": "any",
                      "value": "<string>",
                      "key": "license",
                      "description": "(Required) "
                    },
                    {
                      "description": "Self-hosted Enterprise Server hostname",
                      "type": "any",
                      "value": "{{hostname}}",
                      "key": "hostname"
                    },
                    {
                      "description": "Self-hosted Enterprise Server protocol",
                      "type": "any",
                      "value": "{{protocol}}",
                      "key": "protocol"
                    }
                  ]
                },
                "header": [
                  {
                    "description": {
                      "content": "Added as a part of security scheme: bearer",
                      "type": "text/plain"
                    },
                    "key": "Authorization",
                    "value": "Bearer <token>"
                  }
                ],
                "method": "GET",
                "body": {}
              },
              "status": "Not Modified",
              "code": 304,
              "header": [
                {
                  "key": "Content-Type",
                  "value": "text/plain"
                }
              ],
              "body": "",
              "cookie": [],
              "_postman_previewlanguage": "text"
            },
            {
              "id": "26bbaaff-d0cd-40d8-946c-af28d03c4055",
              "name": "Forbidden",
              "originalRequest": {
                "url": {
                  "path": [
                    "licenses",
                    ":license"
                  ],
                  "host": [
                    "{{baseUrl}}"
                  ],
                  "query": [],
                  "variable": [
                    {
                      "disabled": false,
                      "type": "any",
                      "value": "<string>",
                      "key": "license",
                      "description": "(Required) "
                    },
                    {
                      "description": "Self-hosted Enterprise Server hostname",
                      "type": "any",
                      "value": "{{hostname}}",
                      "key": "hostname"
                    },
                    {
                      "description": "Self-hosted Enterprise Server protocol",
                      "type": "any",
                      "value": "{{protocol}}",
                      "key": "protocol"
                    }
                  ]
                },
                "header": [
                  {
                    "description": {
                      "content": "Added as a part of security scheme: bearer",
                      "type": "text/plain"
                    },
                    "key": "Authorization",
                    "value": "Bearer <token>"
                  },
                  {
                    "key": "Accept",
                    "value": "application/json"
                  }
                ],
                "method": "GET",
                "body": {}
              },
              "status": "Forbidden",
              "code": 403,
              "header": [
                {
                  "key": "Content-Type",
                  "value": "application/json"
                }
              ],
              "body": "{\n  \"message\": \"Example body text\",\n  \"documentation_url\": \"https://api.github.com/repos/octocat/Hello-World\",\n  \"url\": \"https://api.github.com/repos/octocat/Hello-World\",\n  \"status\": \"open\"\n}",
              "cookie": [],
              "_postman_previewlanguage": "json"
            },
            {
              "id": "ebb26153-6aa0-43a5-bd88-17c2d41f3227",
              "name": "Resource not found",
              "originalRequest": {
                "url": {
                  "path": [
                    "licenses",
                    ":license"
                  ],
                  "host": [
                    "{{baseUrl}}"
                  ],
                  "query": [],
                  "variable": [
                    {
                      "disabled": false,
                      "type": "any",
                      "value": "<string>",
                      "key": "license",
                      "description": "(Required) "
                    },
                    {
                      "description": "Self-hosted Enterprise Server hostname",
                      "type": "any",
                      "value": "{{hostname}}",
                      "key": "hostname"
                    },
                    {
                      "description": "Self-hosted Enterprise Server protocol",
                      "type": "any",
                      "value": "{{protocol}}",
                      "key": "protocol"
                    }
                  ]
                },
                "header": [
                  {
                    "description": {
                      "content": "Added as a part of security scheme: bearer",
                      "type": "text/plain"
                    },
                    "key": "Authorization",
                    "value": "Bearer <token>"
                  },
                  {
                    "key": "Accept",
                    "value": "application/json"
                  }
                ],
                "method": "GET",
                "body": {}
              },
              "status": "Not Found",
              "code": 404,
              "header": [
                {
                  "key": "Content-Type",
                  "value": "application/json"
                }
              ],
              "body": "{\n  \"message\": \"Example body text\",\n  \"documentation_url\": \"https://api.github.com/repos/octocat/Hello-World\",\n  \"url\": \"https://api.github.com/repos/octocat/Hello-World\",\n  \"status\": \"open\"\n}",
              "cookie": [],
              "_postman_previewlanguage": "json"
            }
          ],
          "event": [],
          "protocolProfileBehavior": {
            "disableBodyPruning": true
          }
        }
      ],
      "event": []
    }
  ],
  "event": [],
  "variable": [
    {
      "description": {
        "content": "Self-hosted Enterprise Server hostname",
        "type": "text/plain"
      },
      "type": "any",
      "value": "HOSTNAME",
      "key": "hostname"
    },
    {
      "description": {
        "content": "Self-hosted Enterprise Server protocol",
        "type": "text/plain"
      },
      "type": "any",
      "value": "http",
      "key": "protocol"
    },
    {
      "type": "string",
      "value": "{{protocol}}://{{hostname}}/api/v3",
      "key": "baseUrl"
    }
  ],
  "info": {
    "_postman_id": "04b33105-998e-4cdf-bfd3-3d80828e4558",
    "name": "GitHub Licenses API",
    "schema": "https://schema.getpostman.com/json/collection/v2.1.0/collection.json",
    "description": {
      "content": "Use the REST API to retrieve popular open source licenses and information\nabout a particular project's license file.\n\nContact Support:\n Name: Support",
      "type": "text/plain"
    }
  }
}